{
  "contractHash": "652ca4267b43f577f7a41139387110b68a209650c7ce0e918f4013d7f60850ca",
  "lockfileHash": "44136fa355b3678a1146ad16f7e8649e94fb4fc21fe77e8310c060f61caaff8a",
  "schemaVersion": "2.1.0",
  "validatorVersion": "0.1.0",
  "seed": 0,
  "target": "native",
  "startedAt": 1781264101,
  "durationMs": 10,
  "results": [
    {
      "check": "GEO-003",
      "severity": "warn",
      "subject": {
        "kind": "part",
        "id": "0"
      },
      "message": "aabb_overlap: parts 0 and 21 interpenetrate (static pose)",
      "hint": "v0 AABB proxy — the BVH joint-limit sweep lands P1+ (XC-09)"
    },
    {
      "check": "GEO-003",
      "severity": "warn",
      "subject": {
        "kind": "part",
        "id": "0"
      },
      "message": "aabb_overlap: parts 0 and 24 interpenetrate (static pose)",
      "hint": "v0 AABB proxy — the BVH joint-limit sweep lands P1+ (XC-09)"
    },
    {
      "check": "GEO-003",
      "severity": "warn",
      "subject": {
        "kind": "part",
        "id": "0"
      },
      "message": "aabb_overlap: parts 0 and 25 interpenetrate (static pose)",
      "hint": "v0 AABB proxy — the BVH joint-limit sweep lands P1+ (XC-09)"
    },
    {
      "check": "GEO-003",
      "severity": "warn",
      "subject": {
        "kind": "part",
        "id": "1"
      },
      "message": "aabb_overlap: parts 1 and 21 interpenetrate (static pose)",
      "hint": "v0 AABB proxy — the BVH joint-limit sweep lands P1+ (XC-09)"
    },
    {
      "check": "GEO-003",
      "severity": "warn",
      "subject": {
        "kind": "part",
        "id": "1"
      },
      "message": "aabb_overlap: parts 1 and 25 interpenetrate (static pose)",
      "hint": "v0 AABB proxy — the BVH joint-limit sweep lands P1+ (XC-09)"
    },
    {
      "check": "GEO-003",
      "severity": "warn",
      "subject": {
        "kind": "part",
        "id": "1"
      },
      "message": "aabb_overlap: parts 1 and 36 interpenetrate (static pose)",
      "hint": "v0 AABB proxy — the BVH joint-limit sweep lands P1+ (XC-09)"
    },
    {
      "check": "GEO-003",
      "severity": "warn",
      "subject": {
        "kind": "part",
        "id": "1"
      },
      "message": "aabb_overlap: parts 1 and 38 interpenetrate (static pose)",
      "hint": "v0 AABB proxy — the BVH joint-limit sweep lands P1+ (XC-09)"
    },
    {
      "check": "GEO-003",
      "severity": "warn",
      "subject": {
        "kind": "part",
        "id": "2"
      },
      "message": "aabb_overlap: parts 2 and 21 interpenetrate (static pose)",
      "hint": "v0 AABB proxy — the BVH joint-limit sweep lands P1+ (XC-09)"
    },
    {
      "check": "GEO-003",
      "severity": "warn",
      "subject": {
        "kind": "part",
        "id": "2"
      },
      "message": "aabb_overlap: parts 2 and 24 interpenetrate (static pose)",
      "hint": "v0 AABB proxy — the BVH joint-limit sweep lands P1+ (XC-09)"
    },
    {
      "check": "GEO-003",
      "severity": "warn",
      "subject": {
        "kind": "part",
        "id": "2"
      },
      "message": "aabb_overlap: parts 2 and 45 interpenetrate (static pose)",
      "hint": "v0 AABB proxy — the BVH joint-limit sweep lands P1+ (XC-09)"
    },
    {
      "check": "GEO-003",
      "severity": "warn",
      "subject": {
        "kind": "part",
        "id": "2"
      },
      "message": "aabb_overlap: parts 2 and 47 interpenetrate (static pose)",
      "hint": "v0 AABB proxy — the BVH joint-limit sweep lands P1+ (XC-09)"
    },
    {
      "check": "GEO-003",
      "severity": "warn",
      "subject": {
        "kind": "part",
        "id": "3"
      },
      "message": "aabb_overlap: parts 3 and 54 interpenetrate (static pose)",
      "hint": "v0 AABB proxy — the BVH joint-limit sweep lands P1+ (XC-09)"
    },
    {
      "check": "GEO-003",
      "severity": "warn",
      "subject": {
        "kind": "part",
        "id": "3"
      },
      "message": "aabb_overlap: parts 3 and 56 interpenetrate (static pose)",
      "hint": "v0 AABB proxy — the BVH joint-limit sweep lands P1+ (XC-09)"
    },
    {
      "check": "GEO-003",
      "severity": "warn",
      "subject": {
        "kind": "part",
        "id": "4"
      },
      "message": "aabb_overlap: parts 4 and 63 interpenetrate (static pose)",
      "hint": "v0 AABB proxy — the BVH joint-limit sweep lands P1+ (XC-09)"
    },
    {
      "check": "GEO-003",
      "severity": "warn",
      "subject": {
        "kind": "part",
        "id": "4"
      },
      "message": "aabb_overlap: parts 4 and 65 interpenetrate (static pose)",
      "hint": "v0 AABB proxy — the BVH joint-limit sweep lands P1+ (XC-09)"
    },
    {
      "check": "GEO-003",
      "severity": "warn",
      "subject": {
        "kind": "part",
        "id": "6"
      },
      "message": "aabb_overlap: parts 6 and 12 interpenetrate (static pose)",
      "hint": "v0 AABB proxy — the BVH joint-limit sweep lands P1+ (XC-09)"
    },
    {
      "check": "GEO-003",
      "severity": "warn",
      "subject": {
        "kind": "part",
        "id": "9"
      },
      "message": "aabb_overlap: parts 9 and 16 interpenetrate (static pose)",
      "hint": "v0 AABB proxy — the BVH joint-limit sweep lands P1+ (XC-09)"
    },
    {
      "check": "GEO-003",
      "severity": "warn",
      "subject": {
        "kind": "part",
        "id": "9"
      },
      "message": "aabb_overlap: parts 9 and 17 interpenetrate (static pose)",
      "hint": "v0 AABB proxy — the BVH joint-limit sweep lands P1+ (XC-09)"
    },
    {
      "check": "GEO-003",
      "severity": "warn",
      "subject": {
        "kind": "part",
        "id": "9"
      },
      "message": "aabb_overlap: parts 9 and 18 interpenetrate (static pose)",
      "hint": "v0 AABB proxy — the BVH joint-limit sweep lands P1+ (XC-09)"
    },
    {
      "check": "GEO-003",
      "severity": "warn",
      "subject": {
        "kind": "part",
        "id": "9"
      },
      "message": "aabb_overlap: parts 9 and 21 interpenetrate (static pose)",
      "hint": "v0 AABB proxy — the BVH joint-limit sweep lands P1+ (XC-09)"
    },
    {
      "check": "GEO-003",
      "severity": "warn",
      "subject": {
        "kind": "part",
        "id": "9"
      },
      "message": "aabb_overlap: parts 9 and 24 interpenetrate (static pose)",
      "hint": "v0 AABB proxy — the BVH joint-limit sweep lands P1+ (XC-09)"
    },
    {
      "check": "GEO-003",
      "severity": "warn",
      "subject": {
        "kind": "part",
        "id": "9"
      },
      "message": "aabb_overlap: parts 9 and 25 interpenetrate (static pose)",
      "hint": "v0 AABB proxy — the BVH joint-limit sweep lands P1+ (XC-09)"
    },
    {
      "check": "GEO-003",
      "severity": "warn",
      "subject": {
        "kind": "part",
        "id": "9"
      },
      "message": "aabb_overlap: parts 9 and 26 interpenetrate (static pose)",
      "hint": "v0 AABB proxy — the BVH joint-limit sweep lands P1+ (XC-09)"
    },
    {
      "check": "GEO-003",
      "severity": "warn",
      "subject": {
        "kind": "part",
        "id": "13"
      },
      "message": "aabb_overlap: parts 13 and 24 interpenetrate (static pose)",
      "hint": "v0 AABB proxy — the BVH joint-limit sweep lands P1+ (XC-09)"
    },
    {
      "check": "GEO-003",
      "severity": "warn",
      "subject": {
        "kind": "part",
        "id": "13"
      },
      "message": "aabb_overlap: parts 13 and 25 interpenetrate (static pose)",
      "hint": "v0 AABB proxy — the BVH joint-limit sweep lands P1+ (XC-09)"
    },
    {
      "check": "GEO-003",
      "severity": "warn",
      "subject": {
        "kind": "part",
        "id": "13"
      },
      "message": "aabb_overlap: parts 13 and 26 interpenetrate (static pose)",
      "hint": "v0 AABB proxy — the BVH joint-limit sweep lands P1+ (XC-09)"
    },
    {
      "check": "GEO-003",
      "severity": "warn",
      "subject": {
        "kind": "part",
        "id": "13"
      },
      "message": "aabb_overlap: parts 13 and 27 interpenetrate (static pose)",
      "hint": "v0 AABB proxy — the BVH joint-limit sweep lands P1+ (XC-09)"
    },
    {
      "check": "GEO-003",
      "severity": "warn",
      "subject": {
        "kind": "part",
        "id": "19"
      },
      "message": "aabb_overlap: parts 19 and 21 interpenetrate (static pose)",
      "hint": "v0 AABB proxy — the BVH joint-limit sweep lands P1+ (XC-09)"
    },
    {
      "check": "GEO-003",
      "severity": "warn",
      "subject": {
        "kind": "part",
        "id": "19"
      },
      "message": "aabb_overlap: parts 19 and 22 interpenetrate (static pose)",
      "hint": "v0 AABB proxy — the BVH joint-limit sweep lands P1+ (XC-09)"
    },
    {
      "check": "GEO-003",
      "severity": "warn",
      "subject": {
        "kind": "part",
        "id": "19"
      },
      "message": "aabb_overlap: parts 19 and 23 interpenetrate (static pose)",
      "hint": "v0 AABB proxy — the BVH joint-limit sweep lands P1+ (XC-09)"
    },
    {
      "check": "GEO-003",
      "severity": "warn",
      "subject": {
        "kind": "part",
        "id": "20"
      },
      "message": "aabb_overlap: parts 20 and 21 interpenetrate (static pose)",
      "hint": "v0 AABB proxy — the BVH joint-limit sweep lands P1+ (XC-09)"
    },
    {
      "check": "GEO-003",
      "severity": "warn",
      "subject": {
        "kind": "part",
        "id": "20"
      },
      "message": "aabb_overlap: parts 20 and 22 interpenetrate (static pose)",
      "hint": "v0 AABB proxy — the BVH joint-limit sweep lands P1+ (XC-09)"
    },
    {
      "check": "GEO-003",
      "severity": "warn",
      "subject": {
        "kind": "part",
        "id": "24"
      },
      "message": "aabb_overlap: parts 24 and 30 interpenetrate (static pose)",
      "hint": "v0 AABB proxy — the BVH joint-limit sweep lands P1+ (XC-09)"
    },
    {
      "check": "GEO-003",
      "severity": "warn",
      "subject": {
        "kind": "part",
        "id": "25"
      },
      "message": "aabb_overlap: parts 25 and 30 interpenetrate (static pose)",
      "hint": "v0 AABB proxy — the BVH joint-limit sweep lands P1+ (XC-09)"
    },
    {
      "check": "GEO-003",
      "severity": "warn",
      "subject": {
        "kind": "part",
        "id": "26"
      },
      "message": "aabb_overlap: parts 26 and 28 interpenetrate (static pose)",
      "hint": "v0 AABB proxy — the BVH joint-limit sweep lands P1+ (XC-09)"
    },
    {
      "check": "GEO-003",
      "severity": "warn",
      "subject": {
        "kind": "part",
        "id": "26"
      },
      "message": "aabb_overlap: parts 26 and 72 interpenetrate (static pose)",
      "hint": "v0 AABB proxy — the BVH joint-limit sweep lands P1+ (XC-09)"
    },
    {
      "check": "GEO-003",
      "severity": "warn",
      "subject": {
        "kind": "part",
        "id": "30"
      },
      "message": "aabb_overlap: parts 30 and 34 interpenetrate (static pose)",
      "hint": "v0 AABB proxy — the BVH joint-limit sweep lands P1+ (XC-09)"
    },
    {
      "check": "GEO-003",
      "severity": "warn",
      "subject": {
        "kind": "part",
        "id": "30"
      },
      "message": "aabb_overlap: parts 30 and 35 interpenetrate (static pose)",
      "hint": "v0 AABB proxy — the BVH joint-limit sweep lands P1+ (XC-09)"
    },
    {
      "check": "GEO-003",
      "severity": "warn",
      "subject": {
        "kind": "part",
        "id": "33"
      },
      "message": "aabb_overlap: parts 33 and 34 interpenetrate (static pose)",
      "hint": "v0 AABB proxy — the BVH joint-limit sweep lands P1+ (XC-09)"
    },
    {
      "check": "CTR-004",
      "severity": "error",
      "observed": 42.465753424657535,
      "limit": 80.0,
      "units": "%",
      "message": "explode_coverage: 42 % < 80 %",
      "hint": "add explode windows to parts (leader-flag rule lands with slots/equip)"
    },
    {
      "check": "SIM-001",
      "severity": "warn",
      "message": "powertrain_hud_unavailable: sim.battery required for powertrain HUD",
      "hint": "inline motor kv / battery / props enable SIM checks pre-P3"
    }
  ],
  "verdict": "rejected",
  "counts": {
    "parts": 73,
    "faces": 924,
    "vertices": 1250,
    "triangles": 2208
  }
}